setup.cfg
setup.py
pendulumify/__init__.py
pendulumify/pendulumify.py
pendulumify.egg-info/PKG-INFO
pendulumify.egg-info/SOURCES.txt
pendulumify.egg-info/dependency_links.txt
pendulumify.egg-info/top_level.txt