Metadata-Version: 1.1
Name: pendulumify
Version: 1.1.2
Summary: Recursively replace Python standard datetime objects with Pendulum instances
Home-page: https://github.com/SpotOnInc/pendulumify
Author: SpotOn
Author-email: josh@spoton.com
License: MIT
Download-URL: https://github.com/SpotOnInc/pendulumify/archive/v1.1.2.tar.gz
Keywords: pendulum,time,date,datetime
Platform: a
Platform: n
Platform: y
